picobox/__init__.py
picobox/_box.py
picobox/_scopes.py
picobox/_stack.py
picobox/py.typed
picobox/contrib/__init__.py
picobox/contrib/flaskscopes.py
picobox-3.0.0.dist-info/METADATA
picobox-3.0.0.dist-info/WHEEL
picobox-3.0.0.dist-info/licenses/LICENSE
picobox-3.0.0.dist-info/RECORD
