Metadata-Version: 2.1
Name: picobox
Version: 3.0.0
Summary: Dependency injection framework designed with Python in mind.
Project-URL: Documentation, https://picobox.readthedocs.io
Project-URL: Source, https://github.com/ikalnytskyi/picobox
Project-URL: Bugs, https://github.com/ikalnytskyi/picobox/issues
Author-email: Ihor Kalnytskyi <ihor@kalnytskyi.com>
License-Expression: MIT
License-File: LICENSE
Classifier: Intended Audience :: Developers
Classifier: License :: OSI Approved :: MIT License
Classifier: Operating System :: OS Independent
Classifier: Programming Language :: Python
Classifier: Programming Language :: Python :: 3
Classifier: Programming Language :: Python :: 3.7
Classifier: Programming Language :: Python :: 3.8
Classifier: Programming Language :: Python :: 3.9
Classifier: Programming Language :: Python :: 3.10
Classifier: Programming Language :: Python :: 3.11
Classifier: Programming Language :: Python :: Implementation :: CPython
Classifier: Programming Language :: Python :: Implementation :: PyPy
Classifier: Topic :: Software Development :: Libraries
Requires-Python: >=3.7
